{"team":{"name":"捨てられし者たち","tournament_count":1,"win":7,"lose":1,"concat_names":null,"concat_members":null,"name_set":{},"member_set":{},"names":["捨てられし者たち"],"members":["ためりん","ねもねも軍曹","HIRASAWA","YT_サブ_YT","KakigoyaJP","つんつん"]},"tournaments":[{"name":"捨てられし者たち","result":3,"tournament_key":"unite_online_3a","tournament_name":"Winter Tournament 第3回 Aブロック","tournament_date":1643986800000,"player_list":["ためりん","ねもねも軍曹","HIRASAWA","YT_サブ_YT","KakigoyaJP","つんつん"]}],"player_info":{"HIRASAWA":{"latest_team":"捨てられし者たち","rating":1587},"KakigoyaJP":{"latest_team":"捨てられし者たち","rating":1694},"YT_サブ_YT":{"latest_team":"捨てられし者たち","rating":1654},"ためりん":{"latest_team":"捨てられし者たち","rating":1583},"つんつん":{"latest_team":"捨てられし者たち","rating":1583},"ねもねも軍曹":{"latest_team":"捨てられし者たち","rating":1694}},"similar_team":{}}