{"team":{"name":"Eden's of WATAGASIRA","tournament_count":1,"win":0,"lose":1,"concat_names":null,"concat_members":null,"name_set":{},"member_set":{},"names":["Eden's of WATAGASIRA"],"members":["_ミシュル_","卍Taka卍","EvansNyan","スカイレイ","マサヤ8","あえあり"]},"tournaments":[{"name":"Eden's of WATAGASIRA","result":257,"tournament_key":"unite_online_2a","tournament_name":"Winter Tournament 第2回 Aブロック","tournament_date":1641567600000,"player_list":["_ミシュル_","卍Taka卍","EvansNyan","スカイレイ","マサヤ8","あえあり"]}],"similar_team":{"ニンフィアファンクラブ":["_ミシュル_","卍Taka卍","EvansNyan"],"_ミシュル_さんチーム":["_ミシュル_","EvansNyan","あえあり"]}}