{"team":{"name":"ギザみみピチュー","tournament_count":1,"win":0,"lose":1,"concat_names":null,"concat_members":null,"name_set":{},"member_set":{},"names":["ギザみみピチュー"],"members":["ごまぜりー","拘りめがね","ちゃんきむ","あまぎりゅー","流星きらり"]},"tournaments":[{"name":"ギザみみピチュー","result":257,"tournament_key":"unite_online_2a","tournament_name":"Winter Tournament 第2回 Aブロック","tournament_date":1641567600000,"player_list":["ごまぜりー","拘りめがね","ちゃんきむ","あまぎりゅー","流星きらり"]}],"player_info":{"あまぎりゅー":{"latest_team":"ギザみみピチュー","rating":1485},"ごまぜりー":{"latest_team":"ギザみみピチュー","rating":1485},"ちゃんきむ":{"latest_team":"ギザみみピチュー","rating":1485},"拘りめがね":{"latest_team":"ギザみみピチュー","rating":1485},"流星きらり":{"latest_team":"ギザみみピチュー","rating":1485}},"similar_team":{}}