{"team":{"name":"あずきあいす","tournament_count":2,"win":1,"lose":2,"concat_names":null,"concat_members":null,"name_set":{},"member_set":{},"names":["あずきあいす"],"members":["はる・れん","rizeko","HARUTO01","sakurahasu","Azuki・"]},"tournaments":[{"name":"あずきあいす","result":257,"tournament_key":"unite_online_1b","tournament_name":"Winter Tournament 第1回 Bブロック","tournament_date":1638630000000,"player_list":["はる・れん","rizeko","HARUTO01","sakurahasu","Azuki・"]},{"name":"あずきあいす","result":129,"tournament_key":"unite_online_1a","tournament_name":"Winter Tournament 第1回 Aブロック","tournament_date":1638543600000,"player_list":["はる・れん","rizeko","HARUTO01","sakurahasu","Azuki・"]}],"similar_team":{}}