{"team":{"name":"Team 安藤","tournament_count":1,"win":1,"lose":2,"concat_names":null,"concat_members":null,"name_set":{},"member_set":{},"names":["Team 安藤"],"members":["もんぴー","CHISATOU","れーてき","よなさ","雪ノ稚ユキナ"]},"tournaments":[{"name":"Team 安藤","result":33,"tournament_key":"logstare","tournament_name":"LogStare eSports Series Pokémon UNITE Tournament","tournament_date":1636729200000,"player_list":["もんぴー","CHISATOU","れーてき","よなさ","雪ノ稚ユキナ"]}],"player_info":{"CHISATOU":{"latest_team":"Team 安藤","rating":1485},"もんぴー":{"latest_team":"Team 安藤","rating":1485},"よなさ":{"latest_team":"Team 安藤","rating":1485},"れーてき":{"latest_team":"Team 安藤","rating":1485},"雪ノ稚ユキナ":{"latest_team":"Team 安藤","rating":1485}},"similar_team":{}}