{"team":{"name":"ロケット団（公式）","tournament_count":3,"win":3,"lose":3,"concat_names":null,"concat_members":null,"name_set":{},"member_set":{},"names":["R社会人　クライン派","ロケット団（公式）"],"members":["パギ","砂漠の虎","けあれいん","NISI","ファービー"]},"tournaments":[{"name":"ロケット団（公式）","result":33,"tournament_key":"unite_online_2a","tournament_name":"Winter Tournament 第2回 Aブロック","tournament_date":1641567600000,"player_list":["パギ","けあれいん","NISI","砂漠の虎","ファービー"]},{"name":"R社会人　クライン派","result":257,"tournament_key":"unite_online_1b","tournament_name":"Winter Tournament 第1回 Bブロック","tournament_date":1638630000000,"player_list":["パギ","砂漠の虎","けあれいん","NISI","ファービー"]},{"name":"R社会人　クライン派","result":129,"tournament_key":"unite_online_1a","tournament_name":"Winter Tournament 第1回 Aブロック","tournament_date":1638543600000,"player_list":["パギ","砂漠の虎","けあれいん","NISI","ファービー"]}]}