{"team":{"name":"岡崎からやってきた社畜たち。","tournament_count":1,"win":1,"lose":1,"concat_names":null,"concat_members":null,"name_set":{},"member_set":{},"names":["岡崎からやってきた社畜たち。"],"members":["a7","アヴドゥル＿","tositetosite","ぴょんた","すいぎん１６"]},"tournaments":[{"name":"岡崎からやってきた社畜たち。","result":129,"tournament_key":"unite_online_3a","tournament_name":"Winter Tournament 第3回 Aブロック","tournament_date":1643986800000,"player_list":["a7","アヴドゥル＿","tositetosite","ぴょんた","すいぎん１６"]}],"player_info":{"a7":{"latest_team":"岡崎からやってきた社畜たち。","rating":1499},"tositetosite":{"latest_team":"岡崎からやってきた社畜たち。","rating":1499},"すいぎん１６":{"latest_team":"岡崎からやってきた社畜たち。","rating":1499},"ぴょんた":{"latest_team":"岡崎からやってきた社畜たち。","rating":1499},"アヴドゥル＿":{"latest_team":"岡崎からやってきた社畜たち。","rating":1499}},"similar_team":{}}