{"team":{"name":"栄光工業ユナイト部","tournament_count":1,"win":1,"lose":1,"concat_names":null,"concat_members":null,"name_set":{},"member_set":{},"names":["栄光工業ユナイト部"],"members":["PPQ3EQ3","せつの字","とみしゃす","高垣ウォさん","NrKm"]},"tournaments":[{"name":"栄光工業ユナイト部","result":129,"tournament_key":"unite_online_2b","tournament_name":"Winter Tournament 第2回 Bブロック","tournament_date":1641654000000,"player_list":["PPQ3EQ3","せつの字","とみしゃす","高垣ウォさん","NrKm"]}],"player_info":{"NrKm":{"latest_team":"栄光工業ユナイト部","rating":1500},"PPQ3EQ3":{"latest_team":"栄光工業ユナイト部","rating":1500},"せつの字":{"latest_team":"栄光工業ユナイト部","rating":1500},"とみしゃす":{"latest_team":"栄光工業ユナイト部","rating":1500},"高垣ウォさん":{"latest_team":"栄光工業ユナイト部","rating":1500}},"similar_team":{}}