{"team":{"name":"大富豪フレンズとcham物語","tournament_count":1,"win":5,"lose":2,"concat_names":null,"concat_members":null,"name_set":{},"member_set":{},"names":["大富豪フレンズとcham物語"],"members":["cham_06","1ピエロ7","名探偵ぽくを","雲身払車剣","Troll_Master"]},"tournaments":[{"name":"大富豪フレンズとcham物語","result":5,"tournament_key":"uchable","tournament_name":"第2回UCHABLE!! みんなでPokémon UNITE","tournament_date":1643468400000,"player_list":["cham_06","1ピエロ7","名探偵ぽくを","雲身払車剣","Troll_Master"]}],"player_info":{"1ピエロ7":{"latest_team":"経験値未払い","rating":1564},"Troll_Master":{"latest_team":"大富豪フレンズとcham物語","rating":1555},"cham_06":{"latest_team":"大富豪フレンズと麦のきましま","rating":1524},"名探偵ぽくを":{"latest_team":"大富豪フレンズと麦のきましま","rating":1555},"雲身払車剣":{"latest_team":"大富豪フレンズと麦のきましま","rating":1555}},"similar_team":{"大富豪フレンズと麦のきましま":["cham_06","名探偵ぽくを","雲身払車剣"]}}