{"team":{"name":"TYAI","tournament_count":1,"win":0,"lose":1,"latest_tournament_name":"Winter Tournament 第3回 Aブロック","latest_tournament_key":"unite_online_3a","latest_tournament_date":1643986800000,"latest_tournament_rank":257,"names":["TYAI"],"members":["MarGuaX","兩大包","補寶","WhaTheHELL","ShengChieh"]},"tournaments":[{"name":"TYAI","result":257,"tournament_key":"unite_online_3a","tournament_name":"Winter Tournament 第3回 Aブロック","tournament_date":1643986800000,"player_list":["MarGuaX","兩大包","補寶","WhaTheHELL","ShengChieh"]}],"player_info":{"MarGuaX":{"latest_team":"TYAI","rating":1500},"ShengChieh":{"latest_team":"TYAI","rating":1500},"WhaTheHELL":{"latest_team":"TYAI","rating":1500},"兩大包":{"latest_team":"TYAI","rating":1500},"補寶":{"latest_team":"TYAI","rating":1500}},"similar_team":{}}