{"team":{"name":"短パン小僧","tournament_count":1,"win":1,"lose":1,"latest_tournament_name":"Winter Tournament 第2回 Bブロック","latest_tournament_key":"unite_online_2b","latest_tournament_date":1641654000000,"latest_tournament_rank":129,"names":["短パン小僧"],"members":["りくるぅと","usagipyonko","みぃささん","ValenGames","じょいちゃん"]},"tournaments":[{"name":"短パン小僧","result":129,"tournament_key":"unite_online_2b","tournament_name":"Winter Tournament 第2回 Bブロック","tournament_date":1641654000000,"player_list":["りくるぅと","usagipyonko","みぃささん","ValenGames","じょいちゃん"]}],"player_info":{"ValenGames":{"latest_team":"短パン小僧","rating":1500},"usagipyonko":{"latest_team":"短パン小僧","rating":1500},"じょいちゃん":{"latest_team":"短パン小僧","rating":1500},"みぃささん":{"latest_team":"短パン小僧","rating":1500},"りくるぅと":{"latest_team":"短パン小僧","rating":1500}},"similar_team":{}}