{"team":{"name":"Kim0chi","tournament_count":2,"win":7,"lose":2,"latest_tournament_name":"Winter Tournament 第3回 Bブロック","latest_tournament_key":"unite_online_3b","latest_tournament_date":1644073200000,"latest_tournament_rank":65,"names":["Kim0chi"],"members":["KC・emokia","KC・omen","KC・beppooo","KC・fats","abrahamwz","FallenStarZ"]},"tournaments":[{"name":"Kim0chi","result":65,"tournament_key":"unite_online_3b","tournament_name":"Winter Tournament 第3回 Bブロック","tournament_date":1644073200000,"player_list":["KC・emokia","KC・omen","KC・beppooo","KC・fats","abrahamwz","FallenStarZ"]},{"name":"Kim0chi","result":9,"tournament_key":"unite_online_3a","tournament_name":"Winter Tournament 第3回 Aブロック","tournament_date":1643986800000,"player_list":["KC・emokia","KC・omen","KC・beppooo","KC・fats","abrahamwz","FallenStarZ"]}],"player_info":{"FallenStarZ":{"latest_team":"Kim0chi","rating":1559},"KC・beppooo":{"latest_team":"Kim0chi","rating":1559},"KC・emokia":{"latest_team":"Kim0chi","rating":1559},"KC・fats":{"latest_team":"Kim0chi","rating":1559},"KC・omen":{"latest_team":"Kim0chi","rating":1559},"abrahamwz":{"latest_team":"Kim0chi","rating":1559}},"similar_team":{}}