{"team":{"name":"SoRa1さんチーム","tournament_count":2,"win":0,"lose":2,"latest_tournament_name":"Winter Tournament 第2回 Bブロック","latest_tournament_key":"unite_online_2b","latest_tournament_date":1641654000000,"latest_tournament_rank":257,"names":["SoRa1さんチーム"],"members":["SoRa1","Sirokuro2","レバ氏","ハヒぶー","赤色のめりぃ"]},"tournaments":[{"name":"SoRa1さんチーム","result":257,"tournament_key":"unite_online_2b","tournament_name":"Winter Tournament 第2回 Bブロック","tournament_date":1641654000000,"player_list":["SoRa1","Sirokuro2","レバ氏","ハヒぶー","赤色のめりぃ"]},{"name":"SoRa1さんチーム","result":257,"tournament_key":"unite_online_2a","tournament_name":"Winter Tournament 第2回 Aブロック","tournament_date":1641567600000,"player_list":["SoRa1","Sirokuro2","レバ氏","ハヒぶー","赤色のめりぃ"]}],"player_info":{"Sirokuro2":{"latest_team":"SoRa1さんチーム","rating":1470},"SoRa1":{"latest_team":"SoRa1さんチーム","rating":1486},"ハヒぶー":{"latest_team":"SoRa1さんチーム","rating":1486},"レバ氏":{"latest_team":"SoRa1さんチーム","rating":1486},"赤色のめりぃ":{"latest_team":"SoRa1さんチーム","rating":1486}},"similar_team":{}}