{"player":{"collated_name":"Mbaa","win":5,"lose":4,"total":9,"rating":1517,"teams":"ODDSDICES\tWinter Tournament 第1回 Aブロック\t1638543600000\nODDSDICES\tWinter Tournament 第1回 Bブロック\t1638630000000\nODDSDICES\tWinter Tournament 第1回 Bブロック\t1638630000000\nODDSDICES\tWinter Tournament 第1回 Bブロック\t1638630000000\nODDSDICES\tWinter Tournament 第1回 Bブロック\t1638630000000\nYPS\tWinter Tournament 第2回 Aブロック\t1641567600000\nYPS\tWinter Tournament 第2回 Aブロック\t1641567600000\nYPS\tWinter Tournament 第2回 Aブロック\t1641567600000\nYPS\tWinter Tournament 第2回 Bブロック\t1641654000000","hash":"01aabe060d7849d90a3af2adf542374735ded5b9","data":null,"latest":{"team":"YPS","tournament":"Winter Tournament 第2回 Bブロック","date":1641654000000},"entries":4},"tournaments":[{"collated_name":"Mbaa","member_name":"Mbaa","team_name":"YPS","team_result":257,"team_key":161307580,"tournament_key":"unite_online_2b","tournament_name":"Winter Tournament 第2回 Bブロック","tournament_date":1641654000000,"rating":1517,"mates":"SmollSchmoy\trazihel\tColozuz\tVescx\tBeginnerXs\tMbaa","mate_list":["SmollSchmoy","razihel","Colozuz","Vescx","BeginnerXs"]},{"collated_name":"Mbaa","member_name":"Mbaa","team_name":"YPS","team_result":65,"team_key":161306547,"tournament_key":"unite_online_2a","tournament_name":"Winter Tournament 第2回 Aブロック","tournament_date":1641567600000,"rating":1535,"mates":"SmollSchmoy\trazihel\tColozuz\tVescx\tBeginnerXs\tMbaa","mate_list":["SmollSchmoy","razihel","Colozuz","Vescx","BeginnerXs"]},{"collated_name":"Mbaa","member_name":"Mbaa","team_name":"ODDSDICES","team_result":33,"team_key":159781008,"tournament_key":"unite_online_1b","tournament_name":"Winter Tournament 第1回 Bブロック","tournament_date":1638630000000,"rating":1521,"mates":"razihel\taull_\tSmollSchmoy\tMbaa\tOhMySonn\tREINN","mate_list":["razihel","aull_","SmollSchmoy","OhMySonn","REINN"]},{"collated_name":"Mbaa","member_name":"Mbaa","team_name":"ODDSDICES","team_result":257,"team_key":159779600,"tournament_key":"unite_online_1a","tournament_name":"Winter Tournament 第1回 Aブロック","tournament_date":1638543600000,"rating":1484,"mates":"razihel\taull_\tSmollSchmoy\tMbaa\tOhMySonn\tREINN","mate_list":["razihel","aull_","SmollSchmoy","OhMySonn","REINN"]}],"matches":[{"tnmt_key":"unite_online_1a","opponent_team_key":159779549,"opponent_team_name":"NKD","opponent_team_rank":9,"bracket":"","round":1,"winner_key":159779549,"loser_key":159779600,"winner_score":1,"loser_score":0,"opponents":"MTT\tあいみちゃん\tっぺぺ\tアローズ\tクローロ\t瑠川ヨシュア","opponents_list":["MTT","あいみちゃん","っぺぺ","アローズ","クローロ","瑠川ヨシュア"]},{"tnmt_key":"unite_online_1b","opponent_team_key":159780912,"opponent_team_name":"ぞうさん","opponent_team_rank":9,"bracket":"","round":4,"winner_key":159780912,"loser_key":159781008,"winner_score":1,"loser_score":0,"opponents":"SENNEN\tThousanD\tたくま\tでんちゃ\tミニトマトS\t暇人うぃんな","opponents_list":["SENNEN","ThousanD","たくま","でんちゃ","ミニトマトS","暇人うぃんな"]},{"tnmt_key":"unite_online_1b","opponent_team_key":159780957,"opponent_team_name":"himajin","opponent_team_rank":65,"bracket":"","round":3,"winner_key":159781008,"loser_key":159780957,"winner_score":1,"loser_score":0,"opponents":"Shelly0317\tしゅらご\tぜろあ\tまーーや\tリアン・ワン\t少年H・・","opponents_list":["Shelly0317","しゅらご","ぜろあ","まーーや","リアン・ワン","少年H・・"]},{"tnmt_key":"unite_online_1b","opponent_team_key":159780893,"opponent_team_name":"adamas","opponent_team_rank":129,"bracket":"","round":2,"winner_key":159781008,"loser_key":159780893,"winner_score":1,"loser_score":0,"opponents":"CKWB\tSRKYO\twords0424\tチンチロリン\tバブリアス","opponents_list":["CKWB","SRKYO","words0424","チンチロリン","バブリアス"]},{"tnmt_key":"unite_online_1b","opponent_team_key":159781021,"opponent_team_name":"もーりーふぁんたじー","opponent_team_rank":257,"bracket":"","round":1,"winner_key":159781008,"loser_key":159781021,"winner_score":1,"loser_score":0,"opponents":"Harutá/春田\tロクベル\tせるじお\tゆみーと\t毛利元就","opponents_list":["Harutá/春田","ロクベル","せるじお","ゆみーと","毛利元就"]},{"tnmt_key":"unite_online_2a","opponent_team_key":161306545,"opponent_team_name":"ittknさんチーム","opponent_team_rank":33,"bracket":"","round":3,"winner_key":161306545,"loser_key":161306547,"winner_score":1,"loser_score":0,"opponents":"Bellbird\tittkn\tししょー0\tみずりてぃ\tみなとあくあ\tノダミキ","opponents_list":["Bellbird","ittkn","ししょー0","みずりてぃ","みなとあくあ","ノダミキ"]},{"tnmt_key":"unite_online_2a","opponent_team_key":161306550,"opponent_team_name":"医学部受験生","opponent_team_rank":129,"bracket":"","round":2,"winner_key":161306547,"loser_key":161306550,"winner_score":1,"loser_score":0,"opponents":"ILOVEYOU\tkurur\tmosuchaan\tすかい\tちょもす\tナオピーやで","opponents_list":["ILOVEYOU","kurur","mosuchaan","すかい","ちょもす","ナオピーやで"]},{"tnmt_key":"unite_online_2a","opponent_team_key":161306548,"opponent_team_name":"モルガナイト/64の呪い","opponent_team_rank":257,"bracket":"","round":1,"winner_key":161306547,"loser_key":161306548,"winner_score":1,"loser_score":0,"opponents":"SHEIRA\tpmp8J\tアワカ\tネコムートK\t村雨令音\t蒼月","opponents_list":["SHEIRA","pmp8J","アワカ","ネコムートK","村雨令音","蒼月"]},{"tnmt_key":"unite_online_2b","opponent_team_key":161307581,"opponent_team_name":"ふりぃ７さんチーム","opponent_team_rank":129,"bracket":"","round":1,"winner_key":161307581,"loser_key":161307580,"winner_score":1,"loser_score":0,"opponents":"as\tあろち\tいむちゃん\tふりぃ７\tみれかす","opponents_list":["as","あろち","いむちゃん","ふりぃ７","みれかす"]}],"data":null}