{"player":{"collated_name":"みゆきちきち","is_collated":0,"win":0,"lose":1,"total":1,"rating":1500,"teams":"tzt\tWinter Tournament 第1回 Aブロック\t1638543600000","hash":"0226466bd73c8c3513c9f984b0c01eb3c46c7f80","data":null,"latest":{"team":"tzt","tournament":"Winter Tournament 第1回 Aブロック","date":1638543600000},"entries":1},"tournaments":[{"collated_name":"みゆきちきち","member_name":"みゆきちきち","team_name":"tzt","team_result":129,"team_key":159779502,"tournament_key":"unite_online_1a","tournament_name":"Winter Tournament 第1回 Aブロック","tournament_date":1638543600000,"rating":1500,"mates":"みゆきちきち\tra808\t神様の許嫁\thoegaarden\tJB°","mates_hash":[["ra808","98e25f588544c61dd5e3833d0d7207cbd72ad22d",1],["神様の許嫁","fb052b6d41ded47dd87ed7194921b116a81dc07b",1],["hoegaarden","d44c44ae4b15e6c9d6f831d46c3cb176a3016125",1],["JB°","9d3062ba3085bd17f749eac72f46a6b3e7f59a06",1]]}],"matches":[{"tnmt_key":"unite_online_1a","opponent_team_key":159779519,"opponent_team_name":"麦千代子さんチーム","opponent_team_rank":33,"bracket":"","round":2,"winner_key":159779519,"loser_key":159779502,"winner_score":0,"loser_score":0,"opponents":"麦千代子\tうぉるたーA\tたくびん\tぺコら\tむらたく\tばんばばん_","opponents_hash":[["麦千代子","2f4c421a265fecb8906578ce5753c2f39554f011"],["うぉるたーA","575ced91a7e6353cb2c2c51a861713a9c5afbccc"],["たくびん","81587a733917a66956943e7088476a23ffb58d0b"],["ぺコら","0fa4e729acb9c1fc26596b4a6cc2c4a9a9ee6b9a"],["むらたく","90522dfc9f8b1ed51b3051c76c005c22c583afed"],["ばんばばん_","8376f32d5523cff19b95707b1e2555a114df6aff"]]}],"data":null}