{"player":{"collated_name":"KATH","win":1,"lose":2,"total":3,"rating":1483,"hash":"2652fc6fb3b9d76ccc9f6387fb3f2b751839d080","data":null,"latest":{"team":"宙船","tournament":"LogStare eSports Series Pokémon UNITE Tournament","date":1636729200000},"entries":1},"tournaments":[{"collated_name":"KATH","member_name":"KATH","team_name":"宙船","team_result":65,"team_key":392,"tournament_key":"logstare","tournament_name":"LogStare eSports Series Pokémon UNITE Tournament","tournament_date":1636729200000,"rating":1483,"mate_list":["suyasome","solenoider","アマオウ","いさけん","ななはむ7","とぅるお"]}],"matches":[{"tnmt_key":"logstare","opponent_team_key":423,"opponent_team_name":"リザードンの逆襲","opponent_team_rank":25,"opponents":"てんぺす。\tつとっきー\tわんぬ\tdabu\tれしむつべ","bracket":"L","round":2,"winner_key":423,"loser_key":392,"winner_score":1,"loser_score":0,"opponents_list":["てんぺす。","つとっきー","わんぬ","dabu","れしむつべ"]},{"tnmt_key":"logstare","opponent_team_key":463,"opponent_team_name":"Mantis of Axe","opponent_team_rank":33,"opponents":"チカ\tmorus\tサトちゃん\tテル・ブーイ\tピィー\tカメ97\tmaro8910","bracket":"W","round":2,"winner_key":463,"loser_key":392,"winner_score":1,"loser_score":0,"opponents_list":["チカ","morus","サトちゃん","テル・ブーイ","ピィー","カメ97","maro8910"]},{"tnmt_key":"logstare","opponent_team_key":476,"opponent_team_name":"SHA-(6)4 Gaming","opponent_team_rank":65,"opponents":"コクトー\tなんばだ\tANMITSUSHEEP\t志庵さま\tANNIN","bracket":"W","round":1,"winner_key":392,"loser_key":476,"winner_score":1,"loser_score":0,"opponents_list":["コクトー","なんばだ","ANMITSUSHEEP","志庵さま","ANNIN"]}],"data":null}