{"player":{"collated_name":"むくどりん","win":0,"lose":1,"total":1,"rating":1484,"hash":"2acab786e8874d7d1cdb0a86bb0b4fdc090de48f","data":null,"latest":{"team":"現実","tournament":"Winter Tournament 第1回 Aブロック","date":1638543600000},"entries":1},"tournaments":[{"collated_name":"むくどりん","member_name":"むくどりん","team_name":"現実","team_result":129,"team_key":159779635,"tournament_key":"unite_online_1a","tournament_name":"Winter Tournament 第1回 Aブロック","tournament_date":1638543600000,"rating":1484,"mate_list":["mztn","MABUKI","ののる","チヒロウ"]}],"matches":[{"tnmt_key":"unite_online_1a","opponent_team_key":159779721,"opponent_team_name":"Foreign Famous","opponent_team_rank":5,"opponents":"A55DaveYT\tfwii_YT\tPhilYoumusYT\tsosadsamYT\tMythMyth2YT\tLeesin","bracket":"","round":2,"winner_key":159779721,"loser_key":159779635,"winner_score":1,"loser_score":0,"opponents_list":["A55DaveYT","fwii_YT","PhilYoumusYT","sosadsamYT","MythMyth2YT","Leesin"]}],"data":null}