{"player":{"collated_name":"yulis_k","is_collated":0,"win":0,"lose":1,"total":1,"rating":1485,"teams":"ちねけワンダーワールド\t第2回 geegy杯 presented by 攻略大百科＆ZONe\t1640444400000","hash":"2bf61242b5d8cceb21537e2f723ec109f2dd3228","data":null,"latest":{"team":"ちねけワンダーワールド","tournament":"第2回 geegy杯 presented by 攻略大百科＆ZONe","date":1640444400000},"entries":1},"tournaments":[{"collated_name":"yulis_k","member_name":"yulis_k","team_name":"ちねけワンダーワールド","team_result":17,"team_key":24,"tournament_key":"geegy_2","tournament_name":"第2回 geegy杯 presented by 攻略大百科＆ZONe","tournament_date":1640444400000,"rating":1485,"mates":"ゴルパー師匠\tちねけ\tyulis_k\tseriM\tゼラス大魔王","mates_hash":[["ゴルパー師匠","4cc2390aacb732ad536fa617306f518b5119d396",1],["ちねけ","75383825cacbd5135a612687f324d659cc467116",1],["seriM","65f5dffb7c498f49e209c67e90948b17c356bc77",1],["ゼラス大魔王","24ce29172de97080808ff3032521e96ebdcbe52f",1]]}],"matches":[{"tnmt_key":"geegy_2","opponent_team_key":1,"opponent_team_name":"ぐるーんぱんち","opponent_team_rank":1,"bracket":"","round":2,"winner_key":1,"loser_key":24,"winner_score":1,"loser_score":0,"opponents":"しー\tzerosiki0909\tゲマB\tろーぜん\tテケ","opponents_hash":[["しー","16be90e3c1f6174cf7b757c589fce86162413aa9"],["zerosiki0909","36950787948196d1550fbcf1c2be6b4994264129"],["ゲマB","13fe09e774ec14988670f62ffccf07bec1da5a1b"],["ろーぜん","be60cf7a942fd3650e481a3db19313ae72a28b5d"],["テケ","76d8f12e6d426eec8f4da6b49d7efc1160b92054"]]}],"data":null}