{"player":{"collated_name":"熱風","win":1,"lose":1,"total":2,"rating":1499,"hash":"37ec169e6de092985b5ef6916a82b6d312af04d3","data":null,"latest":{"team":"みんなウルトは持ったな？行くぞォ！","tournament":"Winter Tournament 第3回 Aブロック","date":1643986800000},"entries":1},"tournaments":[{"collated_name":"熱風","member_name":"熱風","team_name":"みんなウルトは持ったな？行くぞォ！","team_result":129,"team_key":163498056,"tournament_key":"unite_online_3a","tournament_name":"Winter Tournament 第3回 Aブロック","tournament_date":1643986800000,"rating":1499,"mate_list":["ittkn","みなとあくあ","ししょー0","みずりてぃ","ノダミキ"]}],"matches":[{"tnmt_key":"unite_online_3a","opponent_team_key":163498057,"opponent_team_name":"Eternity","opponent_team_rank":65,"opponents":"루이_Louis\t디벨_Divel\tPisterio\t킨드레드\t헤론","bracket":"","round":2,"winner_key":163498057,"loser_key":163498056,"winner_score":1,"loser_score":0,"opponents_list":["루이_Louis","디벨_Divel","Pisterio","킨드레드","헤론"]},{"tnmt_key":"unite_online_3a","opponent_team_key":163498055,"opponent_team_name":"チームF","opponent_team_rank":257,"opponents":"Tomoeeeee\tなしおー\tHAL0503\tさいたままま\t緋蓮\t金のサトシ","bracket":"","round":1,"winner_key":163498056,"loser_key":163498055,"winner_score":1,"loser_score":0,"opponents_list":["Tomoeeeee","なしおー","HAL0503","さいたままま","緋蓮","金のサトシ"]}],"data":null}