{"player":{"collated_name":"ザクレイ","win":27,"lose":3,"total":30,"rating":1749,"hash":"3b7aee5623b9e7d8124d01338429dcb8fc37d63a","data":{"name":"ザクレイ","aliases":[],"twitter":"Ssb4_Zackray","youtube":["channel/UCfoTAd662mucYxhZo7YHR9A","Zackray / ザクレイ"]},"latest":{"team":"銀河団","tournament":"Winter Tournament 第2回 Bブロック","date":1641654000000},"entries":4},"tournaments":[{"collated_name":"ザクレイ","member_name":"ザクレイ","team_name":"銀河団","team_result":1,"team_key":161307445,"tournament_key":"unite_online_2b","tournament_name":"Winter Tournament 第2回 Bブロック","tournament_date":1641654000000,"rating":1749,"mate_list":["Suix","JPN_Iroas","ObuyanTV","TON","ホタルノケン"]},{"collated_name":"ザクレイ","member_name":"ザクレイ","team_name":"VERSUS","team_result":9,"team_key":159780987,"tournament_key":"unite_online_1b","tournament_name":"Winter Tournament 第1回 Bブロック","tournament_date":1638630000000,"rating":1655,"mate_list":["JPN_Iroas","まめ","Suix","TON","ホタルノケン"]},{"collated_name":"ザクレイ","member_name":"ザクレイ","team_name":"銀河団","team_result":3,"team_key":159779639,"tournament_key":"unite_online_1a","tournament_name":"Winter Tournament 第1回 Aブロック","tournament_date":1638543600000,"rating":1642,"mate_list":["JPN_Iroas","Suix","TON","ホタルノケン"]},{"collated_name":"ザクレイ","member_name":"ザクレイ","team_name":"ObuyanTV・YT","team_result":2,"team_key":154753116,"tournament_key":"unite_online_0","tournament_name":"第0回 公式オンライン大会","tournament_date":1631977200000,"rating":1585,"mate_list":["ObuyanTV","ajun","ゆめおち","あぜる"]}],"matches":[{"tnmt_key":"unite_online_0","opponent_team_key":154753153,"opponent_team_name":"Ruin","opponent_team_rank":1,"opponents":"Ruin\tSupercell\tえふにゃん\tゆめにゃん\tたきしま","bracket":"","round":8,"winner_key":154753153,"loser_key":154753116,"winner_score":2,"loser_score":1,"opponents_list":["Ruin","Supercell","えふにゃん","ゆめにゃん","たきしま"]},{"tnmt_key":"unite_online_0","opponent_team_key":154753036,"opponent_team_name":"Suix","opponent_team_rank":3,"opponents":"Suix\tめろめろん\tBocky\tTON\tJPN_Iroas","bracket":"","round":7,"winner_key":154753116,"loser_key":154753036,"winner_score":2,"loser_score":1,"opponents_list":["Suix","めろめろん","Bocky","TON","JPN_Iroas"]},{"tnmt_key":"unite_online_0","opponent_team_key":154753087,"opponent_team_name":"hiro","opponent_team_rank":5,"opponents":"hiro\t幽霊\tVELL\tにゃっぷ殿下\tヴァッシュ\t竜狩人\tおこま","bracket":"","round":6,"winner_key":154753116,"loser_key":154753087,"winner_score":1,"loser_score":0,"opponents_list":["hiro","幽霊","VELL","にゃっぷ殿下","ヴァッシュ","竜狩人","おこま"]},{"tnmt_key":"unite_online_0","opponent_team_key":154753146,"opponent_team_name":"ROHI","opponent_team_rank":9,"opponents":"ROHI\twoop\tはみゆき\tきまるV\t大天使TIO\tマークーダ","bracket":"","round":5,"winner_key":154753116,"loser_key":154753146,"winner_score":1,"loser_score":0,"opponents_list":["ROHI","woop","はみゆき","きまるV","大天使TIO","マークーダ"]},{"tnmt_key":"unite_online_0","opponent_team_key":154753123,"opponent_team_name":"ふぇありす","opponent_team_rank":17,"opponents":"ふぇありす\tあわい\tAgenio\t薪OG\t清水てとら","bracket":"","round":4,"winner_key":154753116,"loser_key":154753123,"winner_score":1,"loser_score":0,"opponents_list":["ふぇありす","あわい","Agenio","薪OG","清水てとら"]},{"tnmt_key":"unite_online_0","opponent_team_key":154753121,"opponent_team_name":"Yellowtail","opponent_team_rank":33,"opponents":"Yellowtail\tminar\tかな姫\tきむたく乱闘\tたぬさん0\teel\tごちまるごち","bracket":"","round":3,"winner_key":154753116,"loser_key":154753121,"winner_score":1,"loser_score":0,"opponents_list":["Yellowtail","minar","かな姫","きむたく乱闘","たぬさん0","eel","ごちまるごち"]},{"tnmt_key":"unite_online_0","opponent_team_key":154753114,"opponent_team_name":"J_dragon","opponent_team_rank":65,"opponents":"J_dragon\tハイト\tセセリン\tぽりぷて\tヨクバリスゥ\tすきやき225","bracket":"","round":2,"winner_key":154753116,"loser_key":154753114,"winner_score":1,"loser_score":0,"opponents_list":["J_dragon","ハイト","セセリン","ぽりぷて","ヨクバリスゥ","すきやき225"]},{"tnmt_key":"unite_online_0","opponent_team_key":154753117,"opponent_team_name":"野口ひでぇよ","opponent_team_rank":129,"opponents":"野口ひでぇよ\tふーりか\tなかよしたい\tあかちゃんず\tちゅん06","bracket":"","round":1,"winner_key":154753116,"loser_key":154753117,"winner_score":0,"loser_score":0,"opponents_list":["野口ひでぇよ","ふーりか","なかよしたい","あかちゃんず","ちゅん06"]},{"tnmt_key":"unite_online_1a","opponent_team_key":159779695,"opponent_team_name":"プクリンはころがるよどこまでも","opponent_team_rank":1,"opponents":"ヨクガ\tがおすけ\tCKun\tNyack\tMaaLion\tデズ","bracket":"","round":8,"winner_key":159779695,"loser_key":159779639,"winner_score":2,"loser_score":1,"opponents_list":["ヨクガ","がおすけ","CKun","Nyack","MaaLion","デズ"]},{"tnmt_key":"unite_online_1a","opponent_team_key":159779721,"opponent_team_name":"Foreign Famous","opponent_team_rank":5,"opponents":"A55DaveYT\tfwii_YT\tPhilYoumusYT\tsosadsamYT\tMythMyth2YT\tLeesin","bracket":"","round":7,"winner_key":159779639,"loser_key":159779721,"winner_score":1,"loser_score":0,"opponents_list":["A55DaveYT","fwii_YT","PhilYoumusYT","sosadsamYT","MythMyth2YT","Leesin"]},{"tnmt_key":"unite_online_1a","opponent_team_key":159779644,"opponent_team_name":"Fable","opponent_team_rank":9,"opponents":"スライムF\tシエルl\tるいか\tポン\tちょたぴ\tなつじ","bracket":"","round":6,"winner_key":159779639,"loser_key":159779644,"winner_score":1,"loser_score":0,"opponents_list":["スライムF","シエルl","るいか","ポン","ちょたぴ","なつじ"]},{"tnmt_key":"unite_online_1a","opponent_team_key":159779701,"opponent_team_name":"ノオーガブサンダー","opponent_team_rank":17,"opponents":"sheer_cold\tけーちゃんぐ\tばたを\tかっちん\tNicoZzz\tクルネケ","bracket":"","round":5,"winner_key":159779639,"loser_key":159779701,"winner_score":1,"loser_score":0,"opponents_list":["sheer_cold","けーちゃんぐ","ばたを","かっちん","NicoZzz","クルネケ"]},{"tnmt_key":"unite_online_1a","opponent_team_key":159779750,"opponent_team_name":"バクダン炒め","opponent_team_rank":33,"opponents":"ふぁるせっと\tかいわれくん\tみやおみや\tだぶだぶ\tはせれお\tかりのひと","bracket":"","round":4,"winner_key":159779639,"loser_key":159779750,"winner_score":1,"loser_score":0,"opponents_list":["ふぁるせっと","かいわれくん","みやおみや","だぶだぶ","はせれお","かりのひと"]},{"tnmt_key":"unite_online_1a","opponent_team_key":159779652,"opponent_team_name":"UniteUnight","opponent_team_rank":65,"opponents":"tanti\tGumiKo\tたかはし416\tりょまぽん\tしろくまん3","bracket":"","round":3,"winner_key":159779639,"loser_key":159779652,"winner_score":1,"loser_score":0,"opponents_list":["tanti","GumiKo","たかはし416","りょまぽん","しろくまん3"]},{"tnmt_key":"unite_online_1a","opponent_team_key":159779717,"opponent_team_name":"エンジョイファイト","opponent_team_rank":129,"opponents":"レイサト\tよぴ太郎\tアビライ\tきゅぅぴぃー\tKAKu","bracket":"","round":2,"winner_key":159779639,"loser_key":159779717,"winner_score":1,"loser_score":0,"opponents_list":["レイサト","よぴ太郎","アビライ","きゅぅぴぃー","KAKu"]},{"tnmt_key":"unite_online_1b","opponent_team_key":159781076,"opponent_team_name":"神速ヨクバリス","opponent_team_rank":2,"opponents":"りんとサブ\t滅_Me2\tPyi_\t黄瀬やよい\tIrisanderson\tれむぬむん","bracket":"","round":6,"winner_key":159781076,"loser_key":159780987,"winner_score":1,"loser_score":0,"opponents_list":["りんとサブ","滅_Me2","Pyi_","黄瀬やよい","Irisanderson","れむぬむん"]},{"tnmt_key":"unite_online_1b","opponent_team_key":159780971,"opponent_team_name":"黒蠍団","opponent_team_rank":17,"opponents":"なゆゆ_\tキツネさん\tあさてぃん\tみやちんぐ\t花月","bracket":"","round":5,"winner_key":159780987,"loser_key":159780971,"winner_score":1,"loser_score":0,"opponents_list":["なゆゆ_","キツネさん","あさてぃん","みやちんぐ","花月"]},{"tnmt_key":"unite_online_1b","opponent_team_key":159781075,"opponent_team_name":"Alternative","opponent_team_rank":33,"opponents":"ALLN\tsiroー\tTyona\tアルバード\t特攻隊山びこ","bracket":"","round":4,"winner_key":159780987,"loser_key":159781075,"winner_score":1,"loser_score":0,"opponents_list":["ALLN","siroー","Tyona","アルバード","特攻隊山びこ"]},{"tnmt_key":"unite_online_1b","opponent_team_key":159780978,"opponent_team_name":"でらファミリーズ","opponent_team_rank":65,"opponents":"みのーん12\t11H26R1\tYuu88ki444\tぺいぺぺぺい\tでらちゃん1\tXxSIGUMAxX","bracket":"","round":3,"winner_key":159780987,"loser_key":159780978,"winner_score":1,"loser_score":0,"opponents_list":["みのーん12","11H26R1","Yuu88ki444","ぺいぺぺぺい","でらちゃん1","XxSIGUMAxX"]},{"tnmt_key":"unite_online_1b","opponent_team_key":159780914,"opponent_team_name":"RescueCatS","opponent_team_rank":129,"opponents":"nekomaruX\tCR_Bus_LOG\tにょんXL\t春虎\tスィーリ","bracket":"","round":2,"winner_key":159780987,"loser_key":159780914,"winner_score":0,"loser_score":0,"opponents_list":["nekomaruX","CR_Bus_LOG","にょんXL","春虎","スィーリ"]},{"tnmt_key":"unite_online_1b","opponent_team_key":159781043,"opponent_team_name":"毎食","opponent_team_rank":257,"opponents":"マイマイだぉ\tダイアゴナル\tハナブー0_0\t理事長様\tジャグ連\tすゝす","bracket":"","round":1,"winner_key":159780987,"loser_key":159781043,"winner_score":0,"loser_score":0,"opponents_list":["マイマイだぉ","ダイアゴナル","ハナブー0_0","理事長様","ジャグ連","すゝす"]},{"tnmt_key":"unite_online_2b","opponent_team_key":161307681,"opponent_team_name":"Snovv rabbits","opponent_team_rank":2,"opponents":"Noah_xx\trusiero\tvv007\tスラムン\tiamJPN\tこそた","bracket":"","round":9,"winner_key":161307445,"loser_key":161307681,"winner_score":2,"loser_score":0,"opponents_list":["Noah_xx","rusiero","vv007","スラムン","iamJPN","こそた"]},{"tnmt_key":"unite_online_2b","opponent_team_key":161307519,"opponent_team_name":"Altema","opponent_team_rank":3,"opponents":"F0rTe\tYamada\tおぎん\tあかつきまん\tJPN_King\tuni","bracket":"","round":8,"winner_key":161307445,"loser_key":161307519,"winner_score":2,"loser_score":0,"opponents_list":["F0rTe","Yamada","おぎん","あかつきまん","JPN_King","uni"]},{"tnmt_key":"unite_online_2b","opponent_team_key":161307307,"opponent_team_name":"たろう付いてる奴はヤバい","opponent_team_rank":5,"opponents":"止まらねぇ\tどちらさま\tりくたろうー\tきなたろー\tbeーt","bracket":"","round":7,"winner_key":161307445,"loser_key":161307307,"winner_score":1,"loser_score":0,"opponents_list":["止まらねぇ","どちらさま","りくたろうー","きなたろー","beーt"]},{"tnmt_key":"unite_online_2b","opponent_team_key":161307341,"opponent_team_name":"夢追い人はルの最中","opponent_team_rank":9,"opponents":"ミレニア\t鞘師\tkirin\tあああななし\tel_fina\tネコタロス","bracket":"","round":6,"winner_key":161307445,"loser_key":161307341,"winner_score":1,"loser_score":0,"opponents_list":["ミレニア","鞘師","kirin","あああななし","el_fina","ネコタロス"]},{"tnmt_key":"unite_online_2b","opponent_team_key":161307434,"opponent_team_name":"医学部受験生","opponent_team_rank":17,"opponents":"ちょもす\tmosuchaan\tすかい\tkurur\tナオピーやで\tILOVEYOU","bracket":"","round":5,"winner_key":161307445,"loser_key":161307434,"winner_score":1,"loser_score":0,"opponents_list":["ちょもす","mosuchaan","すかい","kurur","ナオピーやで","ILOVEYOU"]},{"tnmt_key":"unite_online_2b","opponent_team_key":161307464,"opponent_team_name":"ユートピア","opponent_team_rank":33,"opponents":"サクセス10\tpetinpetin\tKojiro133\tルッセル\tToraKichi","bracket":"","round":4,"winner_key":161307445,"loser_key":161307464,"winner_score":1,"loser_score":0,"opponents_list":["サクセス10","petinpetin","Kojiro133","ルッセル","ToraKichi"]},{"tnmt_key":"unite_online_2b","opponent_team_key":161307441,"opponent_team_name":"YST","opponent_team_rank":65,"opponents":"ひよーう\t知りませーん\tFuRuYa\t永バナナ\tgraes\tlee_i5","bracket":"","round":3,"winner_key":161307445,"loser_key":161307441,"winner_score":1,"loser_score":0,"opponents_list":["ひよーう","知りませーん","FuRuYa","永バナナ","graes","lee_i5"]},{"tnmt_key":"unite_online_2b","opponent_team_key":161307451,"opponent_team_name":"whitefox","opponent_team_rank":129,"opponents":"藤宮たつき\t黒猫さんだぅ\tいづな丸\t白い虎颯\t株P\t雨夜様","bracket":"","round":2,"winner_key":161307445,"loser_key":161307451,"winner_score":0,"loser_score":0,"opponents_list":["藤宮たつき","黒猫さんだぅ","いづな丸","白い虎颯","株P","雨夜様"]},{"tnmt_key":"unite_online_2b","opponent_team_key":161307448,"opponent_team_name":"おじさんのきんのたま","opponent_team_rank":257,"opponents":"らてらって\tDrycurry\t望月もちお\tyuki_jin\tあんでい\tmacaRoNi","bracket":"","round":1,"winner_key":161307445,"loser_key":161307448,"winner_score":1,"loser_score":0,"opponents_list":["らてらって","Drycurry","望月もちお","yuki_jin","あんでい","macaRoNi"]}],"data":{"name":"ザクレイ","aliases":[],"twitter":"Ssb4_Zackray","youtube":["channel/UCfoTAd662mucYxhZo7YHR9A","Zackray / ザクレイ"]}}