{"player":{"collated_name":"ゆず_VTuber","win":0,"lose":2,"total":2,"rating":1500,"hash":"48f87b16b14fb205f778da0045b73cce67099306","data":null,"latest":{"team":"類人猿","tournament":"Winter Tournament 第2回 Bブロック","date":1641654000000},"entries":2},"tournaments":[{"collated_name":"ゆず_VTuber","member_name":"ゆず_VTuber","team_name":"類人猿","team_result":257,"team_key":161307491,"tournament_key":"unite_online_2b","tournament_name":"Winter Tournament 第2回 Bブロック","tournament_date":1641654000000,"rating":1500,"mate_list":["みずもれ","ty1ra","グミンNico","ネオ_VTuber","月日_イメ"]},{"collated_name":"ゆず_VTuber","member_name":"ゆず_VTuber","team_name":"類人猿","team_result":257,"team_key":161306762,"tournament_key":"unite_online_2a","tournament_name":"Winter Tournament 第2回 Aブロック","tournament_date":1641567600000,"rating":1500,"mate_list":["みずもれ","ty1ra","グミンNico","ネオ_VTuber","月日_イメ"]}],"matches":[{"tnmt_key":"unite_online_2a","opponent_team_key":161306761,"opponent_team_name":"レンぼーいさんチーム","opponent_team_rank":129,"opponents":"レンぼーい\t愚者の金\tDithK\t黒の剣士rqku\tしろくん艸\tkawaharu","bracket":"","round":1,"winner_key":161306761,"loser_key":161306762,"winner_score":0,"loser_score":0,"opponents_list":["レンぼーい","愚者の金","DithK","黒の剣士rqku","しろくん艸","kawaharu"]},{"tnmt_key":"unite_online_2b","opponent_team_key":161307490,"opponent_team_name":"みーやキャット","opponent_team_rank":129,"opponents":"白パンだ\tーみや\tマジステ\tmaronhn07\tBWを愛す\tせろろ","bracket":"","round":1,"winner_key":161307490,"loser_key":161307491,"winner_score":0,"loser_score":0,"opponents_list":["白パンだ","ーみや","マジステ","maronhn07","BWを愛す","せろろ"]}],"data":null}