{"player":{"collated_name":"KEN・Ｔ","win":0,"lose":1,"total":1,"rating":1500,"hash":"59537c0e821820a919a10947c83afe7484e35bb9","data":null,"latest":{"team":"焼肉カンパニ","tournament":"Winter Tournament 第3回 Aブロック","date":1643986800000},"entries":1},"tournaments":[{"collated_name":"KEN・Ｔ","member_name":"KEN・Ｔ","team_name":"焼肉カンパニ","team_result":257,"team_key":163497904,"tournament_key":"unite_online_3a","tournament_name":"Winter Tournament 第3回 Aブロック","tournament_date":1643986800000,"rating":1500,"mate_list":["みみなちゃん","イラ","akira38691","もすらびっと"]}],"matches":[{"tnmt_key":"unite_online_3a","opponent_team_key":163497905,"opponent_team_name":"おぢさんズ","opponent_team_rank":129,"opponents":"キッシュ\tぱんいち\tbellzzz\tららぽーと\tKURORINGO\tUsan7","bracket":"","round":1,"winner_key":163497905,"loser_key":163497904,"winner_score":0,"loser_score":0,"opponents_list":["キッシュ","ぱんいち","bellzzz","ららぽーと","KURORINGO","Usan7"]}],"data":null}