{"player":{"collated_name":"赤猫03","win":6,"lose":2,"total":8,"rating":1593,"hash":"70f28c8d158a376ac2c53c7d99484bfeffae6978","data":null,"latest":{"team":"絶望のヨクバリス","tournament":"Winter Tournament 第3回 Aブロック","date":1643986800000},"entries":2},"tournaments":[{"collated_name":"赤猫03","member_name":"赤猫03","team_name":"絶望のヨクバリス","team_result":5,"team_key":163497987,"tournament_key":"unite_online_3a","tournament_name":"Winter Tournament 第3回 Aブロック","tournament_date":1643986800000,"rating":1593,"mate_list":["チルコ","SAWXD","ゴーリラ","sheik_ssbm","たまたまえ"]},{"collated_name":"赤猫03","member_name":"赤猫03","team_name":"赤猫『こちとらアロー1位やぞ？』","team_result":257,"team_key":161307467,"tournament_key":"unite_online_2b","tournament_name":"Winter Tournament 第2回 Bブロック","tournament_date":1641654000000,"rating":1500,"mate_list":["鯨です","あなたの恋人","るのぴろ","はちみー⛄️"]}],"matches":[{"tnmt_key":"unite_online_2b","opponent_team_key":161307464,"opponent_team_name":"ユートピア","opponent_team_rank":33,"opponents":"サクセス10\tpetinpetin\tKojiro133\tルッセル\tToraKichi","bracket":"","round":1,"winner_key":161307464,"loser_key":161307467,"winner_score":0,"loser_score":0,"opponents_list":["サクセス10","petinpetin","Kojiro133","ルッセル","ToraKichi"]},{"tnmt_key":"unite_online_3a","opponent_team_key":163498062,"opponent_team_name":"爆速ゆたたげ","opponent_team_rank":2,"opponents":"毛利元就\tゆみーと\ttatsro\tajun\tたきしま","bracket":"","round":7,"winner_key":163498062,"loser_key":163497987,"winner_score":1,"loser_score":0,"opponents_list":["毛利元就","ゆみーと","tatsro","ajun","たきしま"]},{"tnmt_key":"unite_online_3a","opponent_team_key":163497966,"opponent_team_name":"りぼんチャンさんチーム","opponent_team_rank":9,"opponents":"りぼんチャン\tリリリりり\tにきチャン\tyolus1ca\tはしば\tDAKARAだよ","bracket":"","round":6,"winner_key":163497987,"loser_key":163497966,"winner_score":1,"loser_score":0,"opponents_list":["りぼんチャン","リリリりり","にきチャン","yolus1ca","はしば","DAKARAだよ"]},{"tnmt_key":"unite_online_3a","opponent_team_key":163497994,"opponent_team_name":"何やってんだって話だよね","opponent_team_rank":17,"opponents":"G9Y6XPH\tマキトッツォ\tおれわる\tあああななし\tぱんちー\tr1chard","bracket":"","round":5,"winner_key":163497987,"loser_key":163497994,"winner_score":1,"loser_score":0,"opponents_list":["G9Y6XPH","マキトッツォ","おれわる","あああななし","ぱんちー","r1chard"]},{"tnmt_key":"unite_online_3a","opponent_team_key":163497981,"opponent_team_name":"GLE Entei","opponent_team_rank":33,"opponents":"Artalus\tlee_jieun\tJeezMo\tloso2k\tMasterJesh\tJmadrian","bracket":"","round":4,"winner_key":163497987,"loser_key":163497981,"winner_score":1,"loser_score":0,"opponents_list":["Artalus","lee_jieun","JeezMo","loso2k","MasterJesh","Jmadrian"]},{"tnmt_key":"unite_online_3a","opponent_team_key":163497991,"opponent_team_name":"no Lucario","opponent_team_rank":65,"opponents":"nLひraithe\tnLひRéßöñgs\tnLひXeer\tnLひBalloon\tnLひSana\tnLひcrowning","bracket":"","round":3,"winner_key":163497987,"loser_key":163497991,"winner_score":1,"loser_score":0,"opponents_list":["nLひraithe","nLひRéßöñgs","nLひXeer","nLひBalloon","nLひSana","nLひcrowning"]},{"tnmt_key":"unite_online_3a","opponent_team_key":163497985,"opponent_team_name":"RYochamaしんそく","opponent_team_rank":129,"opponents":"Lily_Ryo\taoichama\txLuuna\tgliceon\tyuuです\tカルロー","bracket":"","round":2,"winner_key":163497987,"loser_key":163497985,"winner_score":1,"loser_score":0,"opponents_list":["Lily_Ryo","aoichama","xLuuna","gliceon","yuuです","カルロー"]},{"tnmt_key":"unite_online_3a","opponent_team_key":163497986,"opponent_team_name":"YuzuNoix2022","opponent_team_rank":257,"opponents":"noix0608\tりんほ\trIsa\tYuzu20\t寿司好きすぎ\tAecdurn67","bracket":"","round":1,"winner_key":163497987,"loser_key":163497986,"winner_score":1,"loser_score":0,"opponents_list":["noix0608","りんほ","rIsa","Yuzu20","寿司好きすぎ","Aecdurn67"]}],"data":null}