{"player":{"collated_name":"Amyiisp","win":1,"lose":2,"total":3,"rating":1493,"hash":"7ee9a6e7f2fae09f3f80de79c908d177369d9936","data":null,"latest":{"team":"MazeMist","tournament":"Winter Tournament 第2回 Aブロック","date":1641567600000},"entries":2},"tournaments":[{"player":"Amyiisp","member_name":"Amyiisp","team_name":"MazeMist","team_result":129,"team_key":161306874,"tournament_key":"unite_online_2a","tournament_name":"Winter Tournament 第2回 Aブロック","tournament_date":1641567600000,"rating":1493,"mate_list":["Merufy","Mezukung","PunnoReason","MMG_Omzaa_z"]},{"player":"Amyiisp","member_name":"Amyiisp","team_name":"MazeMist","team_result":257,"team_key":159779584,"tournament_key":"unite_online_1a","tournament_name":"Winter Tournament 第1回 Aブロック","tournament_date":1638543600000,"rating":1492,"mate_list":["Merufy","Mezukung","PunnoReason","Jamerin","Kuronekomaji"]}],"matches":[{"tnmt_key":"unite_online_1a","opponent_team_key":159779565,"opponent_team_name":"たつきと愉快な仲間達","opponent_team_rank":129,"opponents":"Ruin\tたきしま\tSupercell\tゆめにゃん\tえふにゃん","bracket":"","round":1,"winner_key":159779565,"loser_key":159779584,"winner_score":1,"loser_score":0,"opponents_list":["Ruin","たきしま","Supercell","ゆめにゃん","えふにゃん"]},{"tnmt_key":"unite_online_2a","opponent_team_key":161306872,"opponent_team_name":"Altema","opponent_team_rank":9,"opponents":"F0rTe\tYamada\tおぎん\tあかつきまん\tJPN_King\tuni","bracket":"","round":2,"winner_key":161306872,"loser_key":161306874,"winner_score":1,"loser_score":0,"opponents_list":["F0rTe","Yamada","おぎん","あかつきまん","JPN_King","uni"]},{"tnmt_key":"unite_online_2a","opponent_team_key":161306875,"opponent_team_name":"人生ユナイトだけ","opponent_team_rank":257,"opponents":"のんのんん\tえび餃子\tおーどなー\tどりOxO\tNia13\tまっちもん","bracket":"","round":1,"winner_key":161306874,"loser_key":161306875,"winner_score":1,"loser_score":0,"opponents_list":["のんのんん","えび餃子","おーどなー","どりOxO","Nia13","まっちもん"]}],"data":null}