{"player":{"collated_name":"みなとあくあ","win":6,"lose":5,"total":11,"rating":1520,"hash":"a562942b95ea545248454b5520b3f1921ae79775","data":null,"latest":{"team":"ittknさんチーム","tournament":"Winter Tournament 第3回 Bブロック","date":1644073200000},"entries":5},"tournaments":[{"player":"みなとあくあ","member_name":"みなとあくあ","team_name":"ittknさんチーム","team_current_name":"ittknさんチーム","team_result":257,"team_key":163498251,"tournament_key":"unite_online_3b","tournament_name":"Winter Tournament 第3回 Bブロック","tournament_date":1644073200000,"rating":1520,"mate_list":["ittkn","ししょー0","みずりてぃ","ノダミキ","熱風"]},{"player":"みなとあくあ","member_name":"みなとあくあ","team_name":"みんなウルトは持ったな？行くぞォ！","team_current_name":"みんなウルトは持ったな？行くぞォ！","team_result":129,"team_key":163498056,"tournament_key":"unite_online_3a","tournament_name":"Winter Tournament 第3回 Aブロック","tournament_date":1643986800000,"rating":1538,"mate_list":["ittkn","ししょー0","みずりてぃ","ノダミキ","熱風"]},{"player":"みなとあくあ","member_name":"みなとあくあ","team_name":"ittknさんチーム","team_current_name":"ittknさんチーム","team_result":65,"team_key":161307747,"tournament_key":"unite_online_2b","tournament_name":"Winter Tournament 第2回 Bブロック","tournament_date":1641654000000,"rating":1542,"mate_list":["ittkn","ししょー0","みずりてぃ","Bellbird","ノダミキ"]},{"player":"みなとあくあ","member_name":"みなとあくあ","team_name":"ittknさんチーム","team_current_name":"ittknさんチーム","team_result":33,"team_key":161306545,"tournament_key":"unite_online_2a","tournament_name":"Winter Tournament 第2回 Aブロック","tournament_date":1641567600000,"rating":1533,"mate_list":["ittkn","ししょー0","みずりてぃ","Bellbird","ノダミキ"]},{"player":"みなとあくあ","member_name":"みなとあくあ","team_name":"みんなウルトは持ったな!!行くぞォ!!","team_current_name":"みんなウルトは持ったな!!行くぞォ!!","team_result":257,"team_key":159780262,"tournament_key":"unite_online_1b","tournament_name":"Winter Tournament 第1回 Bブロック","tournament_date":1638630000000,"rating":1500,"mate_list":["ittkn","ノダミキ","ししょー0","とよつ"]}],"matches":[{"tnmt_key":"unite_online_1b","opponent_team_key":159780151,"opponent_team_name":"ポケぴとぅ","opponent_team_rank":129,"opponents":"ちゅんどの\thanapeta\tかいぴとぅ\tsumath\tMIKANMIKAN\tmirrorsero","bracket":"","round":1,"winner_key":159780151,"loser_key":159780262,"winner_score":0,"loser_score":0,"opponents_list":["ちゅんどの","hanapeta","かいぴとぅ","sumath","MIKANMIKAN","mirrorsero"]},{"tnmt_key":"unite_online_2a","opponent_team_key":161306542,"opponent_team_name":"オータムGames","opponent_team_rank":9,"opponents":"とうや_OG\tNEKOBIYORI\tレシリザ\tSTELLa\tさわちて\tのののの","bracket":"","round":4,"winner_key":161306542,"loser_key":161306545,"winner_score":1,"loser_score":0,"opponents_list":["とうや_OG","NEKOBIYORI","レシリザ","STELLa","さわちて","のののの"]},{"tnmt_key":"unite_online_2a","opponent_team_key":161306547,"opponent_team_name":"YPS","opponent_team_rank":65,"opponents":"SmollSchmoy\trazihel\tColozuz\tVescx\tBeginnerXs\tMbaa","bracket":"","round":3,"winner_key":161306545,"loser_key":161306547,"winner_score":1,"loser_score":0,"opponents_list":["SmollSchmoy","razihel","Colozuz","Vescx","BeginnerXs","Mbaa"]},{"tnmt_key":"unite_online_2a","opponent_team_key":161306543,"opponent_team_name":"あんのんず","opponent_team_rank":129,"opponents":"たぃくん\tよーペコ\tふれあ\tくろうぃ\tてぃっきん\tピロロロロ0","bracket":"","round":2,"winner_key":161306545,"loser_key":161306543,"winner_score":1,"loser_score":0,"opponents_list":["たぃくん","よーペコ","ふれあ","くろうぃ","てぃっきん","ピロロロロ0"]},{"tnmt_key":"unite_online_2a","opponent_team_key":161306546,"opponent_team_name":"今日は無限です！","opponent_team_rank":257,"opponents":"おびたこ\tモドリツ\tシャンブル\tSOLEIL\tヲサメ","bracket":"","round":1,"winner_key":161306545,"loser_key":161306546,"winner_score":1,"loser_score":0,"opponents_list":["おびたこ","モドリツ","シャンブル","SOLEIL","ヲサメ"]},{"tnmt_key":"unite_online_2b","opponent_team_key":161307749,"opponent_team_name":"バクダン炒め","opponent_team_rank":9,"opponents":"ふぁるせっと\tかいわれくん\tみやおみや\tだぶだぶ\tこいいも\tはせれお","bracket":"","round":3,"winner_key":161307749,"loser_key":161307747,"winner_score":1,"loser_score":0,"opponents_list":["ふぁるせっと","かいわれくん","みやおみや","だぶだぶ","こいいも","はせれお"]},{"tnmt_key":"unite_online_2b","opponent_team_key":161307745,"opponent_team_name":"Garc","opponent_team_rank":129,"opponents":"ケン・D・C\tゆーじnakaji\tひたちせ\tSatsuki_ttz\t夕暮れ時の烏\t動く毛玉","bracket":"","round":2,"winner_key":161307747,"loser_key":161307745,"winner_score":1,"loser_score":0,"opponents_list":["ケン・D・C","ゆーじnakaji","ひたちせ","Satsuki_ttz","夕暮れ時の烏","動く毛玉"]},{"tnmt_key":"unite_online_2b","opponent_team_key":161307748,"opponent_team_name":"犬犬","opponent_team_rank":257,"opponents":"いおりの\tるn\trachmani\tNx_Rolan\tSironaEIGFT","bracket":"","round":1,"winner_key":161307747,"loser_key":161307748,"winner_score":1,"loser_score":0,"opponents_list":["いおりの","るn","rachmani","Nx_Rolan","SironaEIGFT"]},{"tnmt_key":"unite_online_3a","opponent_team_key":163498057,"opponent_team_name":"Eternity","opponent_team_rank":65,"opponents":"루이_Louis\t디벨_Divel\tPisterio\t킨드레드\t헤론","bracket":"","round":2,"winner_key":163498057,"loser_key":163498056,"winner_score":1,"loser_score":0,"opponents_list":["루이_Louis","디벨_Divel","Pisterio","킨드레드","헤론"]},{"tnmt_key":"unite_online_3a","opponent_team_key":163498055,"opponent_team_name":"チームF","opponent_team_rank":257,"opponents":"Tomoeeeee\tなしおー\tHAL0503\tさいたままま\t緋蓮\t金のサトシ","bracket":"","round":1,"winner_key":163498056,"loser_key":163498055,"winner_score":1,"loser_score":0,"opponents_list":["Tomoeeeee","なしおー","HAL0503","さいたままま","緋蓮","金のサトシ"]},{"tnmt_key":"unite_online_3b","opponent_team_key":163498250,"opponent_team_name":"FAKE OUT","opponent_team_rank":33,"opponents":"FKO_VirgoBoi\tFKO_BoatMTP\tFKO_Yunyinツ\tFKO_Aräphâz\tFKO_L3VITH4N\tFKO_MrPard","bracket":"","round":1,"winner_key":163498250,"loser_key":163498251,"winner_score":1,"loser_score":0,"opponents_list":["FKO_VirgoBoi","FKO_BoatMTP","FKO_Yunyinツ","FKO_Aräphâz","FKO_L3VITH4N","FKO_MrPard"]}],"data":null}