{"player":{"collated_name":"KC・omen","win":5,"lose":1,"total":6,"rating":1566,"hash":"ad05baf8b17c74453517ed6e2470a58155016ffe","data":null,"latest":{"team":"Kim0chi","tournament":"Winter Tournament 第3回 Aブロック","date":1643986800000},"entries":1},"tournaments":[{"collated_name":"KC・omen","member_name":"KC・omen","team_name":"Kim0chi","team_result":9,"team_key":163497916,"tournament_key":"unite_online_3a","tournament_name":"Winter Tournament 第3回 Aブロック","tournament_date":1643986800000,"rating":1566,"mate_list":["KC・emokia","KC・beppooo","KC・fats","abrahamwz","FallenStarZ"]}],"matches":[{"tnmt_key":"unite_online_3a","opponent_team_key":163497886,"opponent_team_name":"ふぁいやーのごっどばーど","opponent_team_rank":5,"opponents":"Ixveria\trlHusa\tなりなりく\t_Yu_\tイワークぽぽ","bracket":"","round":6,"winner_key":163497886,"loser_key":163497916,"winner_score":1,"loser_score":0,"opponents_list":["Ixveria","rlHusa","なりなりく","_Yu_","イワークぽぽ"]},{"tnmt_key":"unite_online_3a","opponent_team_key":163497899,"opponent_team_name":"Ampharos Brawlers","opponent_team_rank":17,"opponents":"AMPH×Maximus\tAMPH雷BJAZZ\tAMPH雷Combrg\tAMPH雷Yuuki\tAMPH雷VannM\tSuperSenpuu","bracket":"","round":5,"winner_key":163497916,"loser_key":163497899,"winner_score":1,"loser_score":0,"opponents_list":["AMPH×Maximus","AMPH雷BJAZZ","AMPH雷Combrg","AMPH雷Yuuki","AMPH雷VannM","SuperSenpuu"]},{"tnmt_key":"unite_online_3a","opponent_team_key":163497909,"opponent_team_name":"今度こそやっちゃうよ〜","opponent_team_rank":33,"opponents":"あめーじんぐ\tごましヲ\tももたろ社長\tわたべぇ\tトマトバンク\tぷたん421","bracket":"","round":4,"winner_key":163497916,"loser_key":163497909,"winner_score":1,"loser_score":0,"opponents_list":["あめーじんぐ","ごましヲ","ももたろ社長","わたべぇ","トマトバンク","ぷたん421"]},{"tnmt_key":"unite_online_3a","opponent_team_key":163497914,"opponent_team_name":"ツガル地方","opponent_team_rank":65,"opponents":"クーラ\tうつこ\tちぇりる\tてるtete\tやまとたける","bracket":"","round":3,"winner_key":163497916,"loser_key":163497914,"winner_score":1,"loser_score":0,"opponents_list":["クーラ","うつこ","ちぇりる","てるtete","やまとたける"]},{"tnmt_key":"unite_online_3a","opponent_team_key":163766196,"opponent_team_name":"おれのきんにくのほうがつよい","opponent_team_rank":129,"opponents":"爆烈超兄貴\t古神悠VT\t東北の飛び兎YT\t鈴原るる＿\tともえさん\tうに爺Vtuber","bracket":"","round":2,"winner_key":163497916,"loser_key":163766196,"winner_score":1,"loser_score":0,"opponents_list":["爆烈超兄貴","古神悠VT","東北の飛び兎YT","鈴原るる＿","ともえさん","うに爺Vtuber"]},{"tnmt_key":"unite_online_3a","opponent_team_key":163497917,"opponent_team_name":"チームもっち","opponent_team_rank":257,"opponents":"_もっち\tなかずみ\tがるぱごるぱ\tLiiddell\tおくひろ\t星南茶茶子VT","bracket":"","round":1,"winner_key":163497916,"loser_key":163497917,"winner_score":1,"loser_score":0,"opponents_list":["_もっち","なかずみ","がるぱごるぱ","Liiddell","おくひろ","星南茶茶子VT"]}],"data":null}