{"player":{"collated_name":"なはなさた","win":0,"lose":1,"total":1,"rating":1488,"hash":"e30ece285d01e81ad4d972a930ebf3724f18d1bc","data":null,"latest":{"team":"漢！ヤドラン！魂のカウンタージャングル","tournament":"Winter Tournament 第3回 Aブロック","date":1643986800000},"entries":1},"tournaments":[{"player":"なはなさた","member_name":"なはなさた","team_name":"漢！ヤドラン！魂のカウンタージャングル","team_result":257,"team_key":163497967,"tournament_key":"unite_online_3a","tournament_name":"Winter Tournament 第3回 Aブロック","tournament_date":1643986800000,"rating":1488,"mate_list":["atあんど","tomato331","タンポポ","うっちロル"]}],"matches":[{"tnmt_key":"unite_online_3a","opponent_team_key":163497966,"opponent_team_name":"りぼんチャンさんチーム","opponent_team_rank":9,"opponents":"りぼんチャン\tリリリりり\tにきチャン\tyolus1ca\tはしば\tDAKARAだよ","bracket":"","round":1,"winner_key":163497966,"loser_key":163497967,"winner_score":1,"loser_score":0,"opponents_list":["りぼんチャン","リリリりり","にきチャン","yolus1ca","はしば","DAKARAだよ"]}],"data":null}