{"player":{"collated_name":"malulu","win":0,"lose":1,"total":1,"rating":1484,"hash":"075c56039b90a842b9a757768fd0dfe3882d8d42","data":null,"latest":{"team":"Shigechii","tournament":"第0回 公式オンライン大会","date":1631977200000},"entries":1},"tournaments":[{"player":"malulu","member_name":"malulu","team_name":"Shigechii","team_current_name":"Shigechii","team_result":129,"team_key":154753191,"tournament_key":"unite_online_0","tournament_name":"第0回 公式オンライン大会","tournament_date":1631977200000,"rating":1484,"mate_list":["Shigechii","Bossmelo","きんげん","はまずし","まほゆき","かりい"]}],"matches":[{"tnmt_key":"unite_online_0","opponent_team_key":154753192,"opponent_team_name":"TORU1214","opponent_team_rank":65,"opponents":"TORU1214\tけぷこん\tZUNA\tおねきgt\tKyulbis","bracket":"","round":1,"winner_key":154753192,"loser_key":154753191,"winner_score":1,"loser_score":0,"opponents_list":["TORU1214","けぷこん","ZUNA","おねきgt","Kyulbis"]}],"data":null}